audio_zen/__init__.py
audio_zen-0.0.2.dist-info/LICENSE
audio_zen-0.0.2.dist-info/METADATA
audio_zen-0.0.2.dist-info/WHEEL
audio_zen-0.0.2.dist-info/top_level.txt
audio_zen-0.0.2.dist-info/RECORD
