Metadata-Version: 2.1
Name: audio-zen
Version: 0.0.2
Summary: Audio Zen is created for the training of the deep learning-based audio project
Home-page: https://github.com/haoxiangsnr/audio-zen
Author: haoxiangsnr
Author-email: haoxiangsnr@gmail.com
License: UNKNOWN
Platform: UNKNOWN
Classifier: Programming Language :: Python :: 3
Classifier: License :: OSI Approved :: MIT License
Classifier: Operating System :: OS Independent
Requires-Python: >=3.8
